appliance-0.1.dist-info/DESCRIPTION.rst
appliance-0.1.dist-info/METADATA
appliance-0.1.dist-info/RECORD
appliance-0.1.dist-info/WHEEL
appliance-0.1.dist-info/metadata.json
appliance-0.1.dist-info/top_level.txt
quickstart/__init__.py
quickstart/admin.py
quickstart/apps.py
quickstart/models.py
quickstart/serializers.py
quickstart/tests.py
quickstart/urls.py
quickstart/views.py
quickstart/migrations/0001_initial.py
quickstart/migrations/0002_auto_20180117_1331.py
quickstart/migrations/0003_book_booksalescount.py
quickstart/migrations/0004_appliances.py
quickstart/migrations/0005_auto_20180118_1121.py
quickstart/migrations/__init__.py
quickstart/templates/doc.html
