Metadata-Version: 2.0
Name: appliance
Version: 0.1
Summary: A simple Django app to conduct Web-based appliances management.
Home-page: UNKNOWN
Author: Abhishek Kulkarni
Author-email: abhisheksadanand89@gmail.com
License: BSD License
Platform: UNKNOWN
Classifier: Environment :: Web Environment
Classifier: Framework :: Django
